{
  "details": [
    {
      "rh_uid": "984f201d-e91e-4680-a8db-b2dc70e46bcb",
      "rollup_uid": "c929c312-bd36-4469-8989-61b824ecefd6",
      "detail_id": "ef058a3f-b60e-429b-b6e3-14d386eb86ba",
      "distribution_name": "FDA March 17",
      "distribution_date": "2017-01-14T00:00-05:00",
      "ccc_event_id": "53256",
      "check_number": "578945",
      "check_date": "2017-01-15T00:00-05:00",
      "period_end_date": "2017-01-16T00:00-05:00",
      "lm_detail_id": "c3a24455-a92b-4572-b6b5-628a66572104",
      "royalty_amount": 840.00,
      "service_fee_amount": 160.00,
      "collected_amount": 1000.00,
      "post_distribution_flag": true,
      "product_family": "FAS",
      "split_parent_flag": true
    },
    {
      "rh_uid": "671b8b20-7335-4938-988e-1da803efa6e3",
      "rollup_uid": "c929c312-bd36-4469-8989-61b824ecefd6",
      "detail_id": "ef058a3f-b60e-429b-b6e3-14d386eb86ba",
      "distribution_name": "FDA March 17",
      "distribution_date": "2017-01-14T00:00-05:00",
      "ccc_event_id": "53256",
      "check_number": "578945",
      "check_date": "2017-01-15T00:00-05:00",
      "period_end_date": "2017-01-16T00:00-05:00",
      "lm_detail_id": "fbb61f5e-35df-4081-b975-3d88e2a0af78",
      "royalty_amount": 840.00,
      "service_fee_amount": 160.00,
      "collected_amount": 1000.00,
      "post_distribution_flag": true,
      "product_family": "FAS",
      "split_parent_flag": false
    }
  ]
}
