[
  {
    "id": "4aa7d89f-9721-4ad3-a9ab-e267743a2851",
    "batchId": "ea7b6e8d-8454-4052-b639-c0fdb0a3145c",
    "wrWrkInst": 123456789,
    "status": "LOCKED",
    "productFamily": "AACL",
    "numberOfCopies": 10,
    "grossAmount": 30.5979768711,
    "netAmount": 22.9484826533,
    "serviceFeeAmount": 7.6494942178,
    "serviceFee": 0.25000,
    "aaclUsage": {
      "institution": "CORNELL UNIVERSITY",
      "batchPeriodEndDate": "2019-06-30",
      "usageSource": "Feb 2019 TUR",
      "rightLimitation": "PRINT",
      "numberOfPages": 12,
      "detailLicenseeClass": {
        "id": 108,
        "discipline": "Life Sciences",
        "enrollmentProfile": "EXGP"
      },
      "publicationType": {
        "id": "2fe9c0a0-7672-4b56-bc64-9d4125fecf6e",
        "name": "Book",
        "weight": 4.37
      },
      "usageAge": {
        "period": 2019
      },
      "volumeWeight": 3.7000000000,
      "valueWeight": 194.0280000000,
      "volumeShare": 0.3223698541,
      "valueShare": 0.4425795677,
      "totalShare": 0.3824747109
    },
    "rightsholder": {
      "id": "60080587-a225-439c-81af-f016cb33aeac",
      "name": "101 Communications, Ltd.",
      "accountNumber": 2000133267
    },
    "payee": {
      "id": "a5989f7c-fc6f-4e8c-88d4-2fe7bcce8d1f",
      "name": "IEEE - Inst of Electrical and Electronics Engrs",
      "accountNumber": 1000009997
    },
    "comment": "AACL comment 1"
  },
  {
    "id": "d5331924-72e9-43e7-9a7b-446ac09cff53",
    "batchId": "ea7b6e8d-8454-4052-b639-c0fdb0a3145c",
    "wrWrkInst": 123456789,
    "status": "LOCKED",
    "productFamily": "AACL",
    "numberOfCopies": 10,
    "grossAmount": 19.6124629868,
    "netAmount": 14.7093472401,
    "serviceFeeAmount": 4.9031157467,
    "serviceFee": 0.25000,
    "aaclUsage": {
      "institution": "CORNELL UNIVERSITY",
      "batchPeriodEndDate": "2019-06-30",
      "usageSource": "Feb 2017 TUR",
      "rightLimitation": "ALL",
      "numberOfPages": 12,
      "detailLicenseeClass": {
        "id": 110,
        "discipline": "Life Sciences",
        "enrollmentProfile": "EXU4"
      },
      "publicationType": {
        "id": "1f6f1925-7aa1-4b1a-b3a8-8903acc3d18e",
        "name": "STMA Journal",
        "weight": 1.24
      },
      "usageAge": {
        "period": 2017
      },
      "volumeWeight": 7.5000000000,
      "valueWeight": 111.6000000000,
      "volumeShare": 0.9643201543,
      "valueShare": 0.9969261444,
      "totalShare": 0.9806231493
    },
    "rightsholder": {
      "id": "b0e6b1f6-89e9-4767-b143-db0f49f32769",
      "name": "st Contact Publishing",
      "accountNumber": 2000073957
    },
    "payee": {
      "id": "a5989f7c-fc6f-4e8c-88d4-2fe7bcce8d1f",
      "name": "IEEE - Inst of Electrical and Electronics Engrs",
      "accountNumber": 1000009997
    },
    "comment": "AACL comment 2"
  },
  {
    "id": "a96d23a9-a8e7-48e2-9f0e-c0a1ce3a0eab",
    "batchId": "ea7b6e8d-8454-4052-b639-c0fdb0a3145c",
    "wrWrkInst": 100010768,
    "status": "LOCKED",
    "productFamily": "AACL",
    "numberOfCopies": 1,
    "grossAmount": 0.3875370132,
    "netAmount": 0.2906527599,
    "serviceFeeAmount": 0.0968842533,
    "serviceFee": 0.25000,
    "aaclUsage": {
      "institution": "CORNELL UNIVERSITY",
      "batchPeriodEndDate": "2019-06-30",
      "usageSource": "Feb 2017 TUR",
      "rightLimitation": "PRINT",
      "numberOfPages": 1,
      "detailLicenseeClass": {
        "id": 110,
        "discipline": "Life Sciences",
        "enrollmentProfile": "EXU4"
      },
      "publicationType": {
        "id": "1f6f1925-7aa1-4b1a-b3a8-8903acc3d18e",
        "name": "STMA Journal",
        "weight": 1.24
      },
      "usageAge": {
        "period": 2017
      },
      "volumeWeight": 0.2775000000,
      "valueWeight": 0.3441000000,
      "volumeShare": 0.0356798457,
      "valueShare": 0.0030738556,
      "totalShare": 0.0193768507
    },
    "rightsholder": {
      "id": "019acfde-91be-43aa-8871-6305642bcb2c",
      "name": "White Horse Press",
      "accountNumber": 1000024497
    },
    "comment": "AACL comment 3"
  },
  {
    "id": "2b969cb4-4257-4674-b329-f627d60f5c0d",
    "batchId": "ea7b6e8d-8454-4052-b639-c0fdb0a3145c",
    "wrWrkInst": 123456789,
    "status": "LOCKED",
    "productFamily": "AACL",
    "numberOfCopies": 10,
    "grossAmount": 48.3916177394,
    "netAmount": 36.2937133046,
    "serviceFeeAmount": 12.0979044349,
    "serviceFee": 0.25000,
    "aaclUsage": {
      "institution": "CORNELL UNIVERSITY",
      "batchPeriodEndDate": "2019-06-30",
      "usageSource": "Feb 2017 TUR",
      "rightLimitation": "ALL",
      "numberOfPages": 12,
      "detailLicenseeClass": {
        "id": 108,
        "discipline": "Life Sciences",
        "enrollmentProfile": "EXGP"
      },
      "publicationType": {
        "id": "1f6f1925-7aa1-4b1a-b3a8-8903acc3d18e",
        "name": "STMA Journal",
        "weight": 2.71
      },
      "usageAge": {
        "period": 2017
      },
      "baselineId": "f517f5b9-5f34-41f6-8984-67eeadf65ad1",
      "volumeWeight": 7.5000000000,
      "valueWeight": 243.9000000000,
      "volumeShare": 0.6534524069,
      "valueShare": 0.5563380366,
      "totalShare": 0.6048952217
    },
    "rightsholder": {
      "id": "b0e6b1f6-89e9-4767-b143-db0f49f32769",
      "name": "st Contact Publishing",
      "accountNumber": 2000073957
    },
    "payee": {
      "id": "a5989f7c-fc6f-4e8c-88d4-2fe7bcce8d1f",
      "name": "IEEE - Inst of Electrical and Electronics Engrs",
      "accountNumber": 1000009997
    },
    "comment": "AACL baseline usage"
  },
  {
    "id": "c71c0c80-57c0-43d1-9c40-432c7cd112c6",
    "batchId": "ea7b6e8d-8454-4052-b639-c0fdb0a3145c",
    "wrWrkInst": 100010768,
    "status": "LOCKED",
    "productFamily": "AACL",
    "numberOfCopies": 1,
    "grossAmount": 1.0104053895,
    "netAmount": 0.7578040421,
    "serviceFeeAmount": 0.2526013474,
    "serviceFee": 0.25000,
    "aaclUsage": {
      "institution": "CORNELL UNIVERSITY",
      "batchPeriodEndDate": "2019-06-30",
      "usageSource": "Feb 2017 TUR",
      "rightLimitation": "PRINT",
      "numberOfPages": 1,
      "detailLicenseeClass": {
        "id": 108,
        "discipline": "Life Sciences",
        "enrollmentProfile": "EXGP"
      },
      "publicationType": {
        "id": "1f6f1925-7aa1-4b1a-b3a8-8903acc3d18e",
        "name": "STMA Journal",
        "weight": 1.71
      },
      "usageAge": {
        "period": 2017
      },
      "baselineId": "9aeb87ed-5000-4bee-abcb-e3dfc4f84235",
      "volumeWeight": 0.2775000000,
      "valueWeight": 0.4745250000,
      "volumeShare": 0.0241777391,
      "valueShare": 0.0010823957,
      "totalShare": 0.0126300674
    },
    "rightsholder": {
      "id": "b0e6b1f6-89e9-4767-b143-db0f49f32769",
      "name": "st Contact Publishing",
      "accountNumber": 2000073957
    },
    "comment": "AACL baseline usage 2"
  }
]
